ndx_dandi_icephys/__init__.py
ndx_dandi_icephys/spec/ndx-dandi-icephys.extensions.yaml
ndx_dandi_icephys/spec/ndx-dandi-icephys.namespace.yaml
tests/__init__.py
tests/test_io.py
ndx_dandi_icephys-0.4.0.dist-info/LICENSE
ndx_dandi_icephys-0.4.0.dist-info/METADATA
ndx_dandi_icephys-0.4.0.dist-info/WHEEL
ndx_dandi_icephys-0.4.0.dist-info/top_level.txt
ndx_dandi_icephys-0.4.0.dist-info/RECORD
