Metadata-Version: 2.1
Name: ndx-dandi-icephys
Version: 0.4.0
Summary: DandiIcephysMetadata extension.
Home-page: UNKNOWN
Author: Luiz Tauffer and Ben Dichter
Author-email: ben.dichter@gmail.com
License: BSD3
Platform: UNKNOWN
Classifier: Intended Audience :: Developers
Classifier: Intended Audience :: Science/Research
Requires-Dist: pynwb (>=1.0.2)
